archerysec_cli/__init__.py
archerysec_cli/cli/__init__.py
archerysec_cli/cli/cli.py
archerysec_cli/formatters/__init__.py
archerysec_cli/formatters/cli.py
archerysec_cli/formatters/json.py
archerysec_cli/scanners/__init__.py
archerysec_cli/scanners/scanners.py
archerysec_cli/util/__init__.py
archerysec_cli/util/api.py
archerysec_cli/util/check.py
archerysec_cli-3.1.17.dist-info/LICENSE.txt
archerysec_cli-3.1.17.dist-info/METADATA
archerysec_cli-3.1.17.dist-info/WHEEL
archerysec_cli-3.1.17.dist-info/entry_points.txt
archerysec_cli-3.1.17.dist-info/top_level.txt
archerysec_cli-3.1.17.dist-info/RECORD
