Metadata-Version: 2.1
Name: archerysec_cli
Version: 3.1.17
Summary: A commandline tool that wraps the Archerysec REST API for controlling Archery and executing quick, targeted scans.
Home-page: https://github.com/archerysec/archerysec-cli.git
Author: Anand Tiwari
Author-email: 
License: 
Classifier: Topic :: Security
Classifier: Topic :: Software Development :: Quality Assurance
Classifier: Topic :: Software Development :: Testing
Classifier: Topic :: Software Development :: Libraries :: Python Modules
Classifier: Intended Audience :: Developers
Classifier: Intended Audience :: Information Technology
License-File: LICENSE.txt
Requires-Dist: click
Requires-Dist: docker ==5.0.0
Requires-Dist: idna ==2.10
Requires-Dist: jmespath ==0.10.0
Requires-Dist: python-dateutil ==2.8.1
Requires-Dist: PyYAML
Requires-Dist: websocket-client ==0.58.0
Requires-Dist: wget ==3.2
Provides-Extra: dev
Requires-Dist: coverage ; extra == 'dev'
Requires-Dist: ddt ; extra == 'dev'
Requires-Dist: mock ; extra == 'dev'
Requires-Dist: pep8 ; extra == 'dev'
Requires-Dist: pylint ; extra == 'dev'
Requires-Dist: pytest ; extra == 'dev'
Requires-Dist: responses ; extra == 'dev'
